nyxpy/__init__.py
nyxpy/gateway.py
nyxpy/http.py
nyxpy/http_api.py
nyxpy/http_parsers.py
nyxpy/types.py
nyxpy/utils.py
nyxpy-0.2.0.dist-info/licenses/LICENSE
nyxpy-0.2.0.dist-info/METADATA
nyxpy-0.2.0.dist-info/WHEEL
nyxpy-0.2.0.dist-info/top_level.txt
nyxpy-0.2.0.dist-info/RECORD
