Metadata-Version: 2.4
Name: nyxpy
Version: 0.2.0
Summary: Библиотека для взаимодействия с Nyx, бесплатного аналога Discord
Author-email: Nickolay Kushnarenko <kolya@nk.ax>
License: MIT License
Project-URL: Homepage, https://github.com/kolya5544/nyxpy
Project-URL: Issues, https://github.com/kolya5544/nyxpy/issues
Keywords: nyx,websocket,httpx,bots,asyncio,discord
Classifier: Programming Language :: Python :: 3
Classifier: Programming Language :: Python :: 3 :: Only
Classifier: License :: OSI Approved :: MIT License
Classifier: Typing :: Typed
Classifier: Framework :: AsyncIO
Requires-Python: >=3.11
License-File: LICENSE
Requires-Dist: httpx[http2]>=0.28.1
Requires-Dist: websockets>=15.0
Dynamic: license-file
